ch5mpy/__init__.py
ch5mpy/_typing.py
ch5mpy/array/__init__.py
ch5mpy/array/array.py
ch5mpy/array/chunks/__init__.py
ch5mpy/array/chunks/iter.py
ch5mpy/array/chunks/repeated_array.py
ch5mpy/array/chunks/utils.py
ch5mpy/array/flags.py
ch5mpy/array/functions/__init__.py
ch5mpy/array/functions/apply.py
ch5mpy/array/functions/attributes.py
ch5mpy/array/functions/creation_routines.py
ch5mpy/array/functions/element_wise.py
ch5mpy/array/functions/implement.py
ch5mpy/array/functions/routines.py
ch5mpy/array/functions/sort.py
ch5mpy/array/functions/two_arrays.py
ch5mpy/array/io.py
ch5mpy/array/repr.py
ch5mpy/array/view.py
ch5mpy/attributes.py
ch5mpy/dict.py
ch5mpy/functions/__init__.py
ch5mpy/functions/creation_routines.py
ch5mpy/functions/random.py
ch5mpy/functions/types.py
ch5mpy/indexing/__init__.py
ch5mpy/indexing/base.py
ch5mpy/indexing/list.py
ch5mpy/indexing/optimization.py
ch5mpy/indexing/selection.py
ch5mpy/indexing/single.py
ch5mpy/indexing/slice.py
ch5mpy/indexing/special.py
ch5mpy/indexing/utils.py
ch5mpy/io/__init__.py
ch5mpy/io/read.py
ch5mpy/io/write.py
ch5mpy/list.py
ch5mpy/memory_size.py
ch5mpy/names.py
ch5mpy/np.py
ch5mpy/objects/__init__.py
ch5mpy/objects/dataset.py
ch5mpy/objects/group.py
ch5mpy/objects/object.py
ch5mpy/objects/pickle.py
ch5mpy/options.py
ch5mpy/py.typed
ch5mpy/sparse/__init__.py
ch5mpy/sparse/_typing.py
ch5mpy/sparse/base.py
ch5mpy/sparse/coo.py
ch5mpy/sparse/csr.py
ch5mpy/types.py
ch5mpy/utils.py
ch5mpy-0.5.2.dist-info/licenses/LICENSE
ch5mpy-0.5.2.dist-info/WHEEL
ch5mpy-0.5.2.dist-info/METADATA
ch5mpy-0.5.2.dist-info/RECORD
