Metadata-Version: 2.4
Name: ch5mpy
Version: 0.5.2
Summary: Collection of helper tools for reading or writing to h5 files using the h5py library.
Author: Matteo Bouvier
Author-email: Matteo Bouvier <matteo.bouvier@hotmail.fr>
License-Expression: CECILL-B
License-File: LICENSE
Requires-Dist: h5py
Requires-Dist: numpy>=2.0
Requires-Dist: tqdm
Requires-Dist: scipy>=1.13.1
Requires-Python: >=3.10
